IMServicePlugIn/_IMServicePlugIn.abi3.so
IMServicePlugIn/__init__.py
IMServicePlugIn/_metadata.py
pyobjc_framework_IMServicePlugIn-9.2.dist-info/METADATA
pyobjc_framework_IMServicePlugIn-9.2.dist-info/WHEEL
pyobjc_framework_IMServicePlugIn-9.2.dist-info/top_level.txt
pyobjc_framework_IMServicePlugIn-9.2.dist-info/RECORD
