Metadata-Version: 2.1
Name: pyobjc-framework-IMServicePlugIn
Version: 9.2
Summary: Wrappers for the framework IMServicePlugIn on macOS
Home-page: https://github.com/ronaldoussoren/pyobjc
Author: Ronald Oussoren
Author-email: pyobjc-dev@lists.sourceforge.net
License: MIT License
Keywords: PyObjC,IMServicePlugIn
Platform: MacOS X (>=10.7)
Classifier: Development Status :: 5 - Production/Stable
Classifier: Environment :: Console
Classifier: Environment :: MacOS X :: Cocoa
Classifier: Intended Audience :: Developers
Classifier: License :: OSI Approved :: MIT License
Classifier: Natural Language :: English
Classifier: Operating System :: MacOS :: MacOS X
Classifier: Programming Language :: Python
Classifier: Programming Language :: Python :: 3
Classifier: Programming Language :: Python :: 3 :: Only
Classifier: Programming Language :: Python :: 3.7
Classifier: Programming Language :: Python :: 3.8
Classifier: Programming Language :: Python :: 3.9
Classifier: Programming Language :: Python :: 3.10
Classifier: Programming Language :: Python :: 3.11
Classifier: Programming Language :: Python :: Implementation :: CPython
Classifier: Programming Language :: Objective C
Classifier: Topic :: Software Development :: Libraries :: Python Modules
Classifier: Topic :: Software Development :: User Interfaces
Requires-Python: >=3.7
Project-URL: Documentation, https://pyobjc.readthedocs.io/en/latest/
Project-URL: Issue tracker, https://github.com/ronaldoussoren/pyobjc/issues
Project-URL: Repository, https://github.com/ronaldoussoren/pyobjc
Requires-Dist: pyobjc-core (>=9.2)
Requires-Dist: pyobjc-framework-Cocoa (>=9.2)
